{"1001": {"name": "Vanila Cake", "pr": 150, "qn": 44, "category": "Cake"}, "1002": {"name": "Chocolate Cake", "pr": 250, "qn": 20, "category": "Cake"}, "1003": {"name": "strawberry Cake", "pr": 300, "qn": 25, "category": "Cake"}, "1004": {"name": "Milk Cake", "pr": 200, "qn": 35, "category": "Cake"}, "1005": {"name": "Cheese Pizza", "pr": 275, "qn": 15, "category": "Pizza"}, "1006": {"name": "Vege Pizza", "pr": 180, "qn": 15, "category": "Pizza"}, "1007": {"name": "Pattis", "pr": 80, "qn": 26, "category": "Snack"}, "1008": {"name": "Cheese Cake", "pr": 500, "qn": 15, "category": "Cake"}, "1009": {"name": "Cupcakes", "pr": 70, "qn": 50, "category": "Dessert"}, "1010": {"name": "Brownie", "pr": 200, "qn": 70, "category": "Dessert"}, "1011": {"name": "Donut", "pr": 50, "qn": 70, "category": "Dessert"}, "1012": {"name": "Strawberry Pastry", "pr": 50, "qn": 40, "category": "Dessert"}, "1013": {"name": "Mousse", "pr": 110, "qn": 30, "category": "Dessert"}, "1014": {"name": "Burger", "pr": 55, "qn": 40, "category": "Fast Food"}, "1015": {"name": "Cheese Sandwich", "pr": 110, "qn": 25, "category": "Fast Food"}, "1016": {"name": "Vege Sandwich", "pr": 80, "qn": 25, "category": "Fast Food"}, "1017": {"name": "Garlic Bread", "pr": 150, "qn": 15, "category": "Fast Food"}, "1018": {"name": "Brown Bread", "pr": 40, "qn": 20, "category": "Dairy"}, "1019": {"name": "Vanilla Ice-Cream", "pr": 45, "qn": 15, "category": "Dairy"}, "1020": {"name": "Chocolate Ice-Cream", "pr": 55, "qn": 15, "category": "Dairy"}, "1021": {"name": "Coco Powder", "pr": 120, "qn": 13, "category": "Dairy"}, "1022": {"name": "Milk Powder", "pr": 120, "qn": 30, "category": "Dairy"}, "1023": {"name": "Strawberry Ice-Cream", "pr": 70, "qn": 20, "category": "Dairy"}, "1024": {"name": "Candy", "pr": 15, "qn": 60, "category": "Dairy"}, "1025": {"name": "Popsicle", "pr": 20, "qn": 60, "category": "Dairy"}, "1026": {"name": "Chocobar", "pr": 35, "qn": 20, "category": "Dairy"}, "1027": {"name": "Dolly", "pr": 15, "qn": 30, "category": "Dairy"}, "1028": {"name": "Choco Lava", "pr": 45, "qn": 20, "category": "Dessert"}, "1029": {"name": "Hot Dog", "pr": 35, "qn": 25, "category": "Fast Food"}, "1030": {"name": "Buiscuit", "pr": 25, "qn": 60, "category": "Dessert"}}
